poetry_plugin_openfund/__init__.py
poetry_plugin_openfund/openfund.py
poetry_plugin_openfund/plugin.py
poetry_plugin_openfund-0.1.5.dist-info/METADATA
poetry_plugin_openfund-0.1.5.dist-info/WHEEL
poetry_plugin_openfund-0.1.5.dist-info/entry_points.txt
poetry_plugin_openfund-0.1.5.dist-info/RECORD
